flask_yoyo.py
flask_yoyo-0.2.0.dist-info/entry_points.txt
flask_yoyo-0.2.0.dist-info/LICENSE
flask_yoyo-0.2.0.dist-info/WHEEL
flask_yoyo-0.2.0.dist-info/METADATA
flask_yoyo-0.2.0.dist-info/RECORD
